docs/dev/README.md
docs/dev/github.md
docs/dev/pypi.md
docs/dev/settings.md
terraformer/__init__.py
terraformer/_version.py
terraformer/apply_log.py
terraformer/authentication.py
terraformer/exceptions.py
terraformer/mixins.py
terraformer/plan.py
terraformer/py.typed
terraformer/settings.py
terraformer/workspace.py
terraformer/conf/__init__.py
terraformer/conf/settings.py
tests/__init__.py
tests/conftest.py
tests/test_apply_logs.py
tests/test_plan.py
tests/test_workspace.py
tests/terraform/applies/vpc.jsonl
tests/terraform/destroys/vpc.jsonl
tests/terraform/plans/sensitive_plan.json
tests/terraform/plans/test.plan
tests/terraform/workspace/main.tf
tests/terraform/workspace/mock.tfbackend
tests/terraform/workspace/test.auto.tfvars.json
terraformer-0.3.1.dist-info/LICENSE
terraformer-0.3.1.dist-info/METADATA
terraformer-0.3.1.dist-info/WHEEL
terraformer-0.3.1.dist-info/top_level.txt
terraformer-0.3.1.dist-info/RECORD
