Metadata-Version: 2.1
Name: terraformer
Version: 0.3.1
Summary: A python library
Author-email: Robert Hafner <robert@tedivm.com>
License: MIT License
Requires-Python: >=3.10
License-File: LICENSE
Requires-Dist: pydantic
Provides-Extra: dev
Requires-Dist: black ; extra == 'dev'
Requires-Dist: build ; extra == 'dev'
Requires-Dist: dapperdata ; extra == 'dev'
Requires-Dist: glom ; extra == 'dev'
Requires-Dist: isort ; extra == 'dev'
Requires-Dist: mypy ; extra == 'dev'
Requires-Dist: pip-tools ; extra == 'dev'
Requires-Dist: pytest ; extra == 'dev'
Requires-Dist: pytest-cov ; extra == 'dev'
Requires-Dist: pytest-pretty ; extra == 'dev'
Requires-Dist: ruamel.yaml ; extra == 'dev'
Requires-Dist: toml-sort ; extra == 'dev'
